weather_c/__init__.py
weather_c/weather_c.py
weather_c-0.1.9.dist-info/METADATA
weather_c-0.1.9.dist-info/WHEEL
weather_c-0.1.9.dist-info/entry_points.txt
weather_c-0.1.9.dist-info/RECORD
