Metadata-Version: 2.4
Name: weather-c
Version: 0.1.9
Summary: Add your description here
Requires-Python: >=3.13
Requires-Dist: httpx>=0.28.1
Requires-Dist: mcp[cli]>=1.7.1
